satellitetools/__init__.py
satellitetools/aws.py
satellitetools/biophys/__init__.py
satellitetools/biophys/biophys.py
satellitetools/biophys/snap-auxdata/biophysical/2_1/Algo_S2_V2.1_SL2T_FAPAR.xlsx
satellitetools/biophys/snap-auxdata/biophysical/2_1/Algo_S2_V2.1_SL2T_FCOVER.xlsx
satellitetools/biophys/snap-auxdata/biophysical/2_1/Algo_S2_V2.1_SL2T_LAI.xlsx
satellitetools/biophys/snap-auxdata/biophysical/2_1/Algo_S2_V2.1_SL2T_LAI_Cab.xlsx
satellitetools/biophys/snap-auxdata/biophysical/2_1/Algo_S2_V2.1_SL2T_LAI_Cw.xlsx
satellitetools/biophys/snap-auxdata/biophysical/2_1/FAPAR/FAPAR_DefinitionDomain_Grid
satellitetools/biophys/snap-auxdata/biophysical/2_1/FAPAR/FAPAR_DefinitionDomain_MinMax
satellitetools/biophys/snap-auxdata/biophysical/2_1/FAPAR/FAPAR_Denormalisation
satellitetools/biophys/snap-auxdata/biophysical/2_1/FAPAR/FAPAR_ExtremeCases
satellitetools/biophys/snap-auxdata/biophysical/2_1/FAPAR/FAPAR_Normalisation
satellitetools/biophys/snap-auxdata/biophysical/2_1/FAPAR/FAPAR_TestCases
satellitetools/biophys/snap-auxdata/biophysical/2_1/FAPAR/FAPAR_Weights_Layer1_Bias
satellitetools/biophys/snap-auxdata/biophysical/2_1/FAPAR/FAPAR_Weights_Layer1_Neurons
satellitetools/biophys/snap-auxdata/biophysical/2_1/FAPAR/FAPAR_Weights_Layer2_Bias
satellitetools/biophys/snap-auxdata/biophysical/2_1/FAPAR/FAPAR_Weights_Layer2_Neurons
satellitetools/biophys/snap-auxdata/biophysical/2_1/FCOVER/FCOVER_DefinitionDomain_Grid
satellitetools/biophys/snap-auxdata/biophysical/2_1/FCOVER/FCOVER_DefinitionDomain_MinMax
satellitetools/biophys/snap-auxdata/biophysical/2_1/FCOVER/FCOVER_Denormalisation
satellitetools/biophys/snap-auxdata/biophysical/2_1/FCOVER/FCOVER_ExtremeCases
satellitetools/biophys/snap-auxdata/biophysical/2_1/FCOVER/FCOVER_Normalisation
satellitetools/biophys/snap-auxdata/biophysical/2_1/FCOVER/FCOVER_Weights_Layer1_Bias
satellitetools/biophys/snap-auxdata/biophysical/2_1/FCOVER/FCOVER_Weights_Layer1_Neurons
satellitetools-2.1.6.dist-info/METADATA
satellitetools-2.1.6.dist-info/WHEEL
satellitetools-2.1.6.dist-info/licenses/LICENSE
satellitetools-2.1.6.dist-info/RECORD
