Metadata-Version: 2.4
Name: satellitetools
Version: 2.1.6
Summary: Retrieve Sentinel-2 data and calculate biophysical parameters
License: MIT
License-File: LICENSE
Author: Olli Nevalainen
Author-email: olli.nevalainen.fmi@gmail.com
Requires-Python: >=3.10,<4
Classifier: License :: OSI Approved :: MIT License
Classifier: Programming Language :: Python :: 3
Classifier: Programming Language :: Python :: 3.10
Classifier: Programming Language :: Python :: 3.11
Classifier: Programming Language :: Python :: 3.12
Classifier: Programming Language :: Python :: 3.13
Classifier: Programming Language :: Python :: 3.14
Requires-Dist: earthengine-api (>=0.1.334)
Requires-Dist: gcloud (>=0.18.3)
Requires-Dist: numpy (>=1.23.5)
Requires-Dist: pandas (>=2.1.1)
Requires-Dist: pyproj (>=3.7.0,<4.0.0)
Requires-Dist: pystac-client (>=0.7.5)
Requires-Dist: rasterio (>=1.3.4)
Requires-Dist: scipy (>=1.9.3)
Requires-Dist: setuptools (>=70.0.0)
Requires-Dist: shapely (>=2.0.6,<3.0.0)
Requires-Dist: xarray (>=2022.12.0)
Requires-Dist: xmltodict (>=0.13.0)
